chat/__init__.py
chat/exceptions.py
chat/high_level.py
chat/loop.py
chat/session.py
chat/grpc/__init__.py
chat/grpc/model_grpc.py
chat/grpc/model_pb2.py
chat/types/__init__.py
chat/types/data.py
chat/types/subscription.py
chat/types/topic.py
tests/__init__.py
tests/session_test.py
chatapi-0.1.6.dist-info/LICENSE
chatapi-0.1.6.dist-info/METADATA
chatapi-0.1.6.dist-info/WHEEL
chatapi-0.1.6.dist-info/top_level.txt
chatapi-0.1.6.dist-info/RECORD
