Metadata-Version: 2.1
Name: chatapi
Version: 0.1.6
Summary: Python Chat API for Python applications that need instant messaging
Home-page: https://github.com/arseniybanayev/chatapi
Author: Arseniy Banayev
Author-email: arseniy.banayev@gmail.com
License: UNKNOWN
Keywords: chat whatsapp messaging
Platform: UNKNOWN
Classifier: Programming Language :: Python :: 3.6
Classifier: Development Status :: 4 - Beta
Classifier: License :: OSI Approved :: MIT License
Classifier: Natural Language :: English
Classifier: Operating System :: OS Independent
Classifier: Topic :: Communications :: Chat
Classifier: Typing :: Typed
Requires-Python: >=3.6
Requires-Dist: grpclib
Requires-Dist: protobuf
